multilib/__init__.py
multilib/fakepo.py
multilib/multilib.py
python_multilib-1.3.dist-info/DESCRIPTION.rst
python_multilib-1.3.dist-info/METADATA
python_multilib-1.3.dist-info/RECORD
python_multilib-1.3.dist-info/WHEEL
python_multilib-1.3.dist-info/metadata.json
python_multilib-1.3.dist-info/top_level.txt
