Metadata-Version: 2.0
Name: python-multilib
Version: 1.3
Summary: module for determining if a package is multilib
Home-page: https://github.com/Zyzyx/python-multilib.git
Author: Jay Greguske
Author-email: jgregusk@redhat.com
License: GPLv2
Platform: UNKNOWN
Requires-Dist: six
